oncodca/__init__.py
oncodca-0.0.1a1.dist-info/licenses/LICENSE
oncodca-0.0.1a1.dist-info/METADATA
oncodca-0.0.1a1.dist-info/WHEEL
oncodca-0.0.1a1.dist-info/top_level.txt
oncodca-0.0.1a1.dist-info/RECORD
