Metadata-Version: 2.4
Name: OncoDCA
Version: 0.0.1a1
Summary: Oncology Decision Support System - A Python library for oncology decision support and analysis
Author-email: OncoDCA Team <oncodca@oncodca.org>
License: MIT
Project-URL: Homepage, https://github.com/OncoDCA/OncoDCA
Project-URL: Issues, https://github.com/OncoDCA/OncoDCA/issues
Classifier: Development Status :: 2 - Pre-Alpha
Classifier: Intended Audience :: Developers
Classifier: Intended Audience :: Healthcare Industry
Classifier: License :: OSI Approved :: MIT License
Classifier: Programming Language :: Python :: 3
Classifier: Programming Language :: Python :: 3.7
Classifier: Programming Language :: Python :: 3.8
Classifier: Programming Language :: Python :: 3.9
Classifier: Programming Language :: Python :: 3.10
Classifier: Programming Language :: Python :: 3.11
Classifier: Topic :: Scientific/Engineering :: Medical Science Apps.
Requires-Python: >=3.7
License-File: LICENSE
Dynamic: license-file
